script_house/FileSystemOperation.py
script_house/__init__.py
script_house/ops/FileSystemOperation.py
script_house/ops/MarkdownOperation.py
script_house/ops/__init__.py
script_house/utils/ArchiveUtils.py
script_house/utils/FileSystemUtils.py
script_house/utils/JsonUtils.py
script_house/utils/SystemUtils.py
script_house/utils/__init__.py
script_house-1.1.1.dist-info/LICENSE
script_house-1.1.1.dist-info/METADATA
script_house-1.1.1.dist-info/WHEEL
script_house-1.1.1.dist-info/top_level.txt
script_house-1.1.1.dist-info/RECORD
