Metadata-Version: 2.1
Name: script-house
Version: 1.1.1
Summary: a python script house containing handy functions for daily use
Home-page: https://github.com/gustaavv/script-house
Author: Gustav
Author-email: gustaavv.git@yahoo.com
Classifier: Operating System :: Microsoft :: Windows :: Windows 10
Classifier: License :: OSI Approved :: GNU General Public License v3 (GPLv3)
Classifier: Intended Audience :: End Users/Desktop
Classifier: Intended Audience :: System Administrators
Classifier: Intended Audience :: Information Technology
Classifier: Intended Audience :: Other Audience
Classifier: Natural Language :: Chinese (Simplified)
Classifier: Natural Language :: English
Classifier: Programming Language :: Python :: 3
License-File: LICENSE
